html2ft.py
html2ft-1.2.dist-info/METADATA
html2ft-1.2.dist-info/WHEEL
html2ft-1.2.dist-info/entry_points.txt
html2ft-1.2.dist-info/top_level.txt
html2ft-1.2.dist-info/RECORD
