Metadata-Version: 2.4
Name: html2ft
Version: 1.2
Summary: Command line tool to convert HTML to FastHTML FT components
Author-email: Mark Blakeney <mark.blakeney@bullet-systems.net>
License-Expression: GPL-3.0-or-later
Project-URL: Homepage, https://github.com/bulletmark/html2ft
Keywords: fasthtml
Classifier: Programming Language :: Python :: 3
Requires-Python: >=3.10
Requires-Dist: python-fasthtml>=0.4.5
